agent_flow_tdd-2025.4.1.2.dist-info/licenses/LICENSE
src/__init__.py
src/app.py
src/cli.py
src/mcp.py
src/core/__init__.py
src/core/common.py
src/core/utils.py
src/core/utils/__init__.py
src/core/utils/data_masking.py
src/core/utils/env.py
src/core/utils/logger.py
src/core/utils/model_manager.py
src/core/utils/token_validator.py
src/core/utils/version_analyzer.py
agent_flow_tdd-2025.4.1.2.dist-info/METADATA
agent_flow_tdd-2025.4.1.2.dist-info/WHEEL
agent_flow_tdd-2025.4.1.2.dist-info/entry_points.txt
agent_flow_tdd-2025.4.1.2.dist-info/top_level.txt
agent_flow_tdd-2025.4.1.2.dist-info/RECORD
