Metadata-Version: 2.4
Name: agent-flow-tdd
Version: 2025.4.1.2
Summary: Agent Flow TDD - Biblioteca para desenvolvimento orientado a testes com agentes
Author: Ricardo Malnati
Author-email: ricardomalnati@gmail.com
Classifier: Development Status :: 3 - Alpha
Classifier: Intended Audience :: Developers
Classifier: License :: OSI Approved :: MIT License
Classifier: Operating System :: OS Independent
Classifier: Programming Language :: Python :: 3
Classifier: Programming Language :: Python :: 3.9
Classifier: Programming Language :: Python :: 3.10
Classifier: Programming Language :: Python :: 3.11
Classifier: Topic :: Software Development :: Libraries :: Python Modules
Requires-Python: >=3.9
License-File: LICENSE
Requires-Dist: openai>=1.0.0
Requires-Dist: openrouter>=0.3.0
Requires-Dist: google-generativeai>=0.3.0
Requires-Dist: rope>=1.10.0
Requires-Dist: pygithub>=2.1.0
Requires-Dist: python-dotenv>=1.0.0
Requires-Dist: rich>=13.0.0
Requires-Dist: typer>=0.9.0
Requires-Dist: pydantic>=2.0.0
Requires-Dist: requests>=2.31.0
Requires-Dist: tenacity>=8.2.0
Requires-Dist: cachetools>=5.3.0
Requires-Dist: flask>=3.0.0
Requires-Dist: mcp[cli]>=1.6.0
Provides-Extra: dev
Requires-Dist: pytest>=7.0.0; extra == "dev"
Requires-Dist: pytest-cov>=4.1.0; extra == "dev"
Requires-Dist: black>=23.0.0; extra == "dev"
Requires-Dist: isort>=5.12.0; extra == "dev"
Requires-Dist: flake8>=6.1.0; extra == "dev"
Requires-Dist: mypy>=1.5.0; extra == "dev"
Requires-Dist: autoflake>=2.2.0; extra == "dev"
Requires-Dist: commitizen>=3.12.0; extra == "dev"
Provides-Extra: build
Requires-Dist: setuptools>=61.0.0; extra == "build"
Requires-Dist: wheel>=0.40.0; extra == "build"
Requires-Dist: build>=1.0.0; extra == "build"
Requires-Dist: twine>=6.0.0; extra == "build"
Provides-Extra: all
Requires-Dist: pytest>=7.0.0; extra == "all"
Requires-Dist: pytest-cov>=4.1.0; extra == "all"
Requires-Dist: black>=23.0.0; extra == "all"
Requires-Dist: isort>=5.12.0; extra == "all"
Requires-Dist: flake8>=6.1.0; extra == "all"
Requires-Dist: mypy>=1.5.0; extra == "all"
Requires-Dist: autoflake>=2.2.0; extra == "all"
Requires-Dist: commitizen>=3.12.0; extra == "all"
Requires-Dist: setuptools>=61.0.0; extra == "all"
Requires-Dist: wheel>=0.40.0; extra == "all"
Requires-Dist: build>=1.0.0; extra == "all"
Requires-Dist: twine>=6.0.0; extra == "all"
Dynamic: author
Dynamic: author-email
Dynamic: classifier
Dynamic: description
Dynamic: description-content-type
Dynamic: license-file
Dynamic: provides-extra
Dynamic: requires-dist
Dynamic: requires-python
Dynamic: summary
